ismodule/__init__.py
ismodule/fmath/__init__.py
ismodule/fmath/fcalculator/__init__.py
ismodule/fmath/fcalculator/fcal.py
ismodule/fmath/fgeometry/__init__.py
ismodule/fmath/fgeometry/fgeo.py
ismodule/fname/__init__.py
ismodule/fname/isname.py
ismodule-0.0.0.1.dist-info/LICENSE.txt
ismodule-0.0.0.1.dist-info/METADATA
ismodule-0.0.0.1.dist-info/WHEEL
ismodule-0.0.0.1.dist-info/top_level.txt
ismodule-0.0.0.1.dist-info/RECORD
